{
	"asset" : {
		"version" : "1.0"
	},
	"properties" : {
		"attributes" : {},
		"name" : {},
		"rank" : {},
		"rank_code" : {
			"minimum" : 1,
			"maximum" : 5
		},
		"rank_org" : {},
		"rank_org_code" : {}
	},
	"geometricError" : 1141.1803632057622,
	"root" : {
		"boundingVolume" : {
			"region" : [ 2.4286252992057085, 0.6224879837094722, 2.4318926733621433, 0.6235196612838532, 135.737, 897.386 ]
		},
		"geometricError" : 1141.1803632057622,
		"refine" : "REPLACE",
		"content" : {
			"boundingVolume" : {
				"region" : [ 2.4286252992057085, 0.622500317605873, 2.4318693750228317, 0.6235196612838532, 135.737, 897.386 ]
			},
			"uri" : "data/data34.b3dm"
		},
		"children" : [
			{
				"boundingVolume" : {
					"region" : [ 2.430152666836727, 0.6230038224966626, 2.4318926733621433, 0.6235196612838532, 135.737, 349.78 ]
				},
				"geometricError" : 1139.9794416547236,
				"refine" : "REPLACE",
				"content" : {
					"boundingVolume" : {
						"region" : [ 2.430152666836727, 0.6230823181671027, 2.4318693750228317, 0.6235187448459949, 135.737, 349.78 ]
					},
					"uri" : "data/data12.b3dm"
				},
				"children" : [
					{
						"boundingVolume" : {
							"region" : [ 2.431024727126432, 0.6232272080387955, 2.4318926733621433, 0.6235196612838532, 139.727, 248.139 ]
						},
						"geometricError" : 1140.0320590802598,
						"refine" : "REPLACE",
						"content" : {
							"boundingVolume" : {
								"region" : [ 2.431024727126432, 0.6232272080387955, 2.4317392382760046, 0.6235187448459949, 139.727, 248.139 ]
							},
							"uri" : "data/data4.b3dm"
						},
						"children" : [
							{
								"boundingVolume" : {
									"region" : [ 2.431461868881148, 0.6233726429268992, 2.4318926733621433, 0.6235196612838532, 144.23499999995693, 165.209 ]
								},
								"geometricError" : 0,
								"refine" : "REPLACE",
								"content" : {
									"boundingVolume" : {
										"region" : [ 2.431461868881148, 0.6233726429268992, 2.431668883876279, 0.6234662294020351, 144.23499999995693, 165.209 ]
									},
									"uri" : "data/data0.b3dm"
								},
								"children" : []
							},
							{
								"boundingVolume" : {
									"region" : [ 2.4310758298230346, 0.6233732233985968, 2.4314842515925887, 0.6235196612838532, 153.88799999980256, 180.283 ]
								},
								"geometricError" : 0,
								"refine" : "REPLACE",
								"content" : {
									"boundingVolume" : {
										"region" : [ 2.4312435261268295, 0.6233732233985968, 2.4314624725056864, 0.6235187448459949, 153.88799999980256, 180.283 ]
									},
									"uri" : "data/data1.b3dm"
								},
								"children" : []
							},
							{
								"boundingVolume" : {
									"region" : [ 2.431460860749777, 0.6232272080387955, 2.4318926733621433, 0.6233907015870556, 139.727, 227.125 ]
								},
								"geometricError" : 0,
								"refine" : "REPLACE",
								"content" : {
									"boundingVolume" : {
										"region" : [ 2.431460860749777, 0.6232272080387955, 2.4317392382760046, 0.6233867676694347, 139.727, 227.125 ]
									},
									"uri" : "data/data2.b3dm"
								},
								"children" : []
							},
							{
								"boundingVolume" : {
									"region" : [ 2.431024727126432, 0.6232282277896116, 2.4314842625675803, 0.6234045354141879, 150.668, 248.139 ]
								},
								"geometricError" : 0,
								"refine" : "REPLACE",
								"content" : {
									"boundingVolume" : {
										"region" : [ 2.431024727126432, 0.6232282277896116, 2.4314842625675803, 0.6234045354141879, 150.668, 248.139 ]
									},
									"uri" : "data/data3.b3dm"
								},
								"children" : []
							}
						]
					},
					{
						"boundingVolume" : {
							"region" : [ 2.430152666836727, 0.6232516767597761, 2.4310758298230346, 0.6235196612838532, 166.298, 349.78 ]
						},
						"geometricError" : 1134.2769488625315,
						"refine" : "REPLACE",
						"content" : {
							"boundingVolume" : {
								"region" : [ 2.430152666836727, 0.6232516767597761, 2.4310250062047896, 0.6233742188560762, 166.298, 349.78 ]
							},
							"uri" : "data/data7.b3dm"
						},
						"children" : [
							{
								"boundingVolume" : {
									"region" : [ 2.4305886201566382, 0.6232516767597761, 2.4310758298230346, 0.6233907015870556, 165.359, 299.0940000002738 ]
								},
								"geometricError" : 0,
								"refine" : "REPLACE",
								"content" : {
									"boundingVolume" : {
										"region" : [ 2.4305886201566382, 0.6232516767597761, 2.431067386918782, 0.6233741513890315, 165.359, 299.0940000002738 ]
									},
									"uri" : "data/data5.b3dm"
								},
								"children" : []
							},
							{
								"boundingVolume" : {
									"region" : [ 2.430152666836727, 0.6232608326866539, 2.4306735948130305, 0.6233907015870556, 176.494, 349.78 ]
								},
								"geometricError" : 0,
								"refine" : "REPLACE",
								"content" : {
									"boundingVolume" : {
										"region" : [ 2.430152666836727, 0.6232608326866539, 2.4306735948130305, 0.6233742188560762, 176.494, 349.78 ]
									},
									"uri" : "data/data6.b3dm"
								},
								"children" : []
							}
						]
					},
					{
						"boundingVolume" : {
							"region" : [ 2.4310758298230346, 0.6230038224966626, 2.4318926733621433, 0.623261741890258, 134.259, 226.722 ]
						},
						"geometricError" : 954.7861161877403,
						"refine" : "REPLACE",
						"content" : {
							"boundingVolume" : {
								"region" : [ 2.4313340619682515, 0.6230605101095483, 2.4318887976222525, 0.6232596219995576, 134.259, 226.722 ]
							},
							"uri" : "data/data11.b3dm"
						},
						"children" : [
							{
								"boundingVolume" : {
									"region" : [ 2.4314842515925887, 0.6230823181671027, 2.4318926733621433, 0.6232621464910172, 135.737, 226.722 ]
								},
								"geometricError" : 0,
								"refine" : "REPLACE",
								"content" : {
									"boundingVolume" : {
										"region" : [ 2.431503928184672, 0.6230823181671027, 2.4318693750228317, 0.6232621464910172, 135.737, 226.722 ]
									},
									"uri" : "data/data8.b3dm"
								},
								"children" : []
							},
							{
								"boundingVolume" : {
									"region" : [ 2.4310758298230346, 0.6231327821934602, 2.4314842515925887, 0.623261741890258, 200.802, 222.008 ]
								},
								"geometricError" : 0,
								"refine" : "REPLACE",
								"content" : {
									"boundingVolume" : {
										"region" : [ 2.4313340619682515, 0.6232269241379984, 2.431438351042005, 0.6232500994186799, 200.802, 222.008 ]
									},
									"uri" : "data/data9.b3dm"
								},
								"children" : []
							},
							{
								"boundingVolume" : {
									"region" : [ 2.4314842515925887, 0.6230038224966626, 2.4318926733621433, 0.6231327821934602, 134.087, 136.461 ]
								},
								"geometricError" : 0,
								"refine" : "REPLACE",
								"content" : {
									"boundingVolume" : {
										"region" : [ 2.4317920248498894, 0.6230573791839286, 2.4318926733621433, 0.6231151849430905, 134.087, 136.461 ]
									},
									"uri" : "data/data10.b3dm"
								},
								"children" : []
							}
						]
					}
				]
			},
			{
				"boundingVolume" : {
					"region" : [ 2.4286252992057085, 0.6229364467261284, 2.430258986283926, 0.6235196612838532, 209.57, 704.883 ]
				},
				"geometricError" : 1141.0353833040847,
				"refine" : "REPLACE",
				"content" : {
					"boundingVolume" : {
						"region" : [ 2.429279237808783, 0.6229364467261284, 2.4301531230828064, 0.6235196612838532, 209.57, 704.883 ]
					},
					"uri" : "data/data23.b3dm"
				},
				"children" : [
					{
						"boundingVolume" : {
							"region" : [ 2.4294421427448167, 0.6232272054926002, 2.430258986283926, 0.6235196612838532, 209.57, 551.3369999984279 ]
						},
						"geometricError" : 1135.8628512937298,
						"refine" : "REPLACE",
						"content" : {
							"boundingVolume" : {
								"region" : [ 2.4294987298015074, 0.6232272054926002, 2.4301531230828064, 0.6235196612838532, 209.57, 551.3369999984279 ]
							},
							"uri" : "data/data17.b3dm"
						},
						"children" : [
							{
								"boundingVolume" : {
									"region" : [ 2.429841154243002, 0.6233726492917216, 2.430258986283926, 0.6235196612838532, 209.015, 362.176 ]
								},
								"geometricError" : 0,
								"refine" : "REPLACE",
								"content" : {
									"boundingVolume" : {
										"region" : [ 2.429841154243002, 0.6233726492917216, 2.4301537878537256, 0.6235196612838532, 209.015, 362.176 ]
									},
									"uri" : "data/data13.b3dm"
								},
								"children" : []
							},
							{
								"boundingVolume" : {
									"region" : [ 2.4294421427448167, 0.6233729331627784, 2.4299346831214192, 0.6235196612838532, 210.396, 404.444 ]
								},
								"geometricError" : 0,
								"refine" : "REPLACE",
								"content" : {
									"boundingVolume" : {
										"region" : [ 2.429715578389113, 0.6233729331627784, 2.4299346831214192, 0.6235196574653633, 210.396, 404.444 ]
									},
									"uri" : "data/data14.b3dm"
								},
								"children" : []
							},
							{
								"boundingVolume" : {
									"region" : [ 2.4298505645143713, 0.623261741890258, 2.4302762342671533, 0.6233907015870556, 248.864, 370.921 ]
								},
								"geometricError" : 0,
								"refine" : "REPLACE",
								"content" : {
									"boundingVolume" : {
										"region" : [ 2.4298594542575676, 0.6233122038044824, 2.4302762342671533, 0.6233905623329387, 248.864, 370.921 ]
									},
									"uri" : "data/data15.b3dm"
								},
								"children" : []
							},
							{
								"boundingVolume" : {
									"region" : [ 2.4294421427448167, 0.6232272054926002, 2.4298505645143713, 0.6233921382418107, 265.783, 551.3369999984279 ]
								},
								"geometricError" : 0,
								"refine" : "REPLACE",
								"content" : {
									"boundingVolume" : {
										"region" : [ 2.4294987298015074, 0.6232272054926002, 2.4298479054306923, 0.6233921382418107, 265.783, 551.3369999984279 ]
									},
									"uri" : "data/data16.b3dm"
								},
								"children" : []
							}
						]
					},
					{
						"boundingVolume" : {
							"region" : [ 2.4294421427448167, 0.6229376054865537, 2.430258986283926, 0.623261741890258, 342.709, 685.413 ]
						},
						"geometricError" : 1130.121813298505,
						"refine" : "REPLACE",
						"content" : {
							"boundingVolume" : {
								"region" : [ 2.4294973610632695, 0.6229376054865537, 2.4297217165451293, 0.6232555303531406, 342.709, 685.413 ]
							},
							"uri" : "data/data20.b3dm"
						},
						"children" : [
							{
								"boundingVolume" : {
									"region" : [ 2.4294421427448167, 0.6230823398120159, 2.4298505645143713, 0.6232618638704158, 338.366, 671.267 ]
								},
								"geometricError" : 0,
								"refine" : "REPLACE",
								"content" : {
									"boundingVolume" : {
										"region" : [ 2.429498021130622, 0.6230823398120159, 2.4297217165451293, 0.6232618638704158, 338.366, 671.267 ]
									},
									"uri" : "data/data18.b3dm"
								},
								"children" : []
							},
							{
								"boundingVolume" : {
									"region" : [ 2.4294421427448167, 0.6229376054865537, 2.4298505645143713, 0.6231327821934602, 474.991, 685.413 ]
								},
								"geometricError" : 0,
								"refine" : "REPLACE",
								"content" : {
									"boundingVolume" : {
										"region" : [ 2.429443574197293, 0.6229376054865537, 2.4295859229740597, 0.6231297349979777, 474.991, 685.413 ]
									},
									"uri" : "data/data19.b3dm"
								},
								"children" : []
							}
						]
					},
					{
						"boundingVolume" : {
							"region" : [ 2.4286252992057085, 0.6229364467261284, 2.4294992895260794, 0.623261741890258, 395.581, 704.883 ]
						},
						"geometricError" : 1141.08802072735,
						"refine" : "REPLACE",
						"content" : {
							"boundingVolume" : {
								"region" : [ 2.429279237808783, 0.6229364467261284, 2.4294992895260794, 0.6230833303847353, 395.581, 704.883 ]
							},
							"uri" : "data/data22.b3dm"
						},
						"children" : [
							{
								"boundingVolume" : {
									"region" : [ 2.429033720975263, 0.6229364467261284, 2.4294992895260794, 0.6231327821934602, 395.581, 704.883 ]
								},
								"geometricError" : 0,
								"refine" : "REPLACE",
								"content" : {
									"boundingVolume" : {
										"region" : [ 2.429279237808783, 0.6229364467261284, 2.4294992895260794, 0.6230833303847353, 395.581, 704.883 ]
									},
									"uri" : "data/data21.b3dm"
								},
								"children" : []
							}
						]
					}
				]
			},
			{
				"boundingVolume" : {
					"region" : [ 2.4286252992057085, 0.6224879837094722, 2.430258986283926, 0.6230038224966626, 455.831, 897.386 ]
				},
				"geometricError" : 1141.075146908459,
				"refine" : "REPLACE",
				"content" : {
					"boundingVolume" : {
						"region" : [ 2.4286252992057085, 0.6224879837094722, 2.4294986278908715, 0.622937885626292, 455.831, 897.386 ]
					},
					"uri" : "data/data33.b3dm"
				},
				"children" : [
					{
						"boundingVolume" : {
							"region" : [ 2.4294421427448167, 0.6227459031030674, 2.430258986283926, 0.6230038224966626, 480.632, 607.01 ]
						},
						"geometricError" : 230.07801167591288,
						"refine" : "REPLACE",
						"content" : {
							"boundingVolume" : {
								"region" : [ 2.429442533140947, 0.6229014236921602, 2.429502411127262, 0.6229939620999273, 480.632, 607.01 ]
							},
							"uri" : "data/data25.b3dm"
						},
						"children" : [
							{
								"boundingVolume" : {
									"region" : [ 2.4294421427448167, 0.6228748627998649, 2.4298505645143713, 0.6230038224966626, 480.632, 617.996 ]
								},
								"geometricError" : 0,
								"refine" : "REPLACE",
								"content" : {
									"boundingVolume" : {
										"region" : [ 2.429442533140947, 0.6228824448737261, 2.429502411127262, 0.6229939926593917, 480.632, 617.996 ]
									},
									"uri" : "data/data24.b3dm"
								},
								"children" : []
							}
						]
					},
					{
						"boundingVolume" : {
							"region" : [ 2.4286252992057085, 0.6227439135662997, 2.4294986278908715, 0.6230038224966626, 435.432, 832.4099999996834 ]
						},
						"geometricError" : 1141.1277574349901,
						"refine" : "REPLACE",
						"content" : {
							"boundingVolume" : {
								"region" : [ 2.428842858032055, 0.6227439135662997, 2.4294986278908715, 0.6230014071295626, 435.432, 832.4099999996834 ]
							},
							"uri" : "data/data29.b3dm"
						},
						"children" : [
							{
								"boundingVolume" : {
									"region" : [ 2.429033720975263, 0.6228658331016512, 2.4294986278908715, 0.6230059935637761, 428.488, 770.248 ]
								},
								"geometricError" : 0,
								"refine" : "REPLACE",
								"content" : {
									"boundingVolume" : {
										"region" : [ 2.4290374603116867, 0.6228658331016512, 2.4294986278908715, 0.6230059935637761, 428.488, 770.248 ]
									},
									"uri" : "data/data26.b3dm"
								},
								"children" : []
							},
							{
								"boundingVolume" : {
									"region" : [ 2.4286252992057085, 0.6228748627998649, 2.429033720975263, 0.6230038224966626, 649.658, 654.051 ]
								},
								"geometricError" : 0,
								"refine" : "REPLACE",
								"content" : {
									"boundingVolume" : {
										"region" : [ 2.4290240143791197, 0.622925616726287, 2.4290259553847777, 0.6229271995286989, 649.658, 654.051 ]
									},
									"uri" : "data/data27.b3dm"
								},
								"children" : []
							},
							{
								"boundingVolume" : {
									"region" : [ 2.4286252992057085, 0.6227439135662997, 2.4290628768243767, 0.6229378830795675, 454.777, 832.4099999996834 ]
								},
								"geometricError" : 0,
								"refine" : "REPLACE",
								"content" : {
									"boundingVolume" : {
										"region" : [ 2.428842858032055, 0.6227439135662997, 2.4290628768243767, 0.6229378830795675, 454.777, 832.4099999996834 ]
									},
									"uri" : "data/data28.b3dm"
								},
								"children" : []
							}
						]
					},
					{
						"boundingVolume" : {
							"region" : [ 2.4286252992057085, 0.6224879837094722, 2.4294421427448167, 0.6227917035980253, 493.908, 897.386 ]
						},
						"geometricError" : 1133.48962730473,
						"refine" : "REPLACE",
						"content" : {
							"boundingVolume" : {
								"region" : [ 2.4286252992057085, 0.6224879837094722, 2.428988533799133, 0.6227917035980253, 493.908, 897.386 ]
							},
							"uri" : "data/data32.b3dm"
						},
						"children" : [
							{
								"boundingVolume" : {
									"region" : [ 2.4286252992057085, 0.6226164722567838, 2.429033720975263, 0.6227917035980253, 493.908, 795.404 ]
								},
								"geometricError" : 0,
								"refine" : "REPLACE",
								"content" : {
									"boundingVolume" : {
										"region" : [ 2.4286580877770416, 0.6226164722567838, 2.428988533799133, 0.6227917035980253, 493.908, 795.404 ]
									},
									"uri" : "data/data30.b3dm"
								},
								"children" : []
							},
							{
								"boundingVolume" : {
									"region" : [ 2.4286252992057085, 0.6224879837094722, 2.429033720975263, 0.6226469950945883, 553.89, 897.386 ]
								},
								"geometricError" : 0,
								"refine" : "REPLACE",
								"content" : {
									"boundingVolume" : {
										"region" : [ 2.4286252992057085, 0.6224879837094722, 2.4289069598222803, 0.6226469950945883, 553.89, 897.386 ]
									},
									"uri" : "data/data31.b3dm"
								},
								"children" : []
							}
						]
					}
				]
			}
		]
	}
}